{
  "@id": "dtmi:no:energymanager:asset:AirHandlingUnit;1",
  "@type": "Interface",
  "contents": [
    {
      "@type": "Property",
      "displayName": {
        "en": "Zone delivery"
      },
      "name": "zoneDelivery",
      "schema": {
        "@type": "Enum",
        "enumValues": [
          {
            "enumValue": "VAVZone",
            "name": "VAVZone",
            "displayName": {
              "en": "VAV zone"
            }
          },
          {
            "enumValue": "MultiZone",
            "name": "MultiZone",
            "displayName": {
              "en": "Multi-zone"
            }
          },
          {
            "enumValue": "DirectZone",
            "name": "DirectZone",
            "displayName": {
              "en": "Direct zone"
            }
          },
          {
            "enumValue": "ChilledBeamZone",
            "name": "ChilledBeamZone",
            "displayName": {
              "en": "Chilled beam zone"
            }
          }
        ],
        "valueSchema": "string"
      },
      "writable": true
    },
    {
      "@type": "Property",
      "displayName": {
        "en": "Ventilation strategy"
      },
      "name": "ventilationStrategy",
      "schema": {
        "@type": "Enum",
        "enumValues": [
          {
            "enumValue": "None",
            "name": "None",
            "displayName": {
              "en": "None"
            }
          },
          {
            "enumValue": "Economizing",
            "name": "Economizing",
            "displayName": {
              "en": "Economizing"
            }
          },
          {
            "enumValue": "DemandEconomizing",
            "name": "DemandEconomizing",
            "displayName": {
              "en": "Demand-economizing"
            }
          },
          {
            "enumValue": "Demand",
            "name": "Demand",
            "displayName": {
              "en": "Demand"
            }
          }
        ],
        "valueSchema": "string"
      },
      "writable": true
    },
    {
      "@type": "Property",
      "displayName": {
        "en": "Ventilation configuration"
      },
      "name": "ventilationConfiguration",
      "schema": {
        "@type": "Enum",
        "enumValues": [
          {
            "enumValue": "OA",
            "name": "OA",
            "displayName": {
              "en": "OA"
            }
          },
          {
            "enumValue": "None",
            "name": "None",
            "displayName": {
              "en": "None"
            }
          },
          {
            "enumValue": "MixedAir",
            "name": "MixedAir",
            "displayName": {
              "en": "Mixed-air"
            }
          }
        ],
        "valueSchema": "string"
      },
      "writable": true
    },
    {
      "@type": "Property",
      "displayName": {
        "en": "Refrigerant type"
      },
      "name": "refrigerantType",
      "schema": "string",
      "writable": true
    },
    {
      "@type": "Property",
      "displayName": {
        "en": "Nominal heating capacity"
      },
      "name": "nominalHeatingCapacity",
      "schema": "double",
      "writable": true
    },
    {
      "@type": "Property",
      "displayName": {
        "en": "Nominal cooling capacity"
      },
      "name": "nominalCoolingCapacity",
      "schema": "double",
      "writable": true
    },
    {
      "@type": "Property",
      "displayName": {
        "en": "Net sensible cooling capacity"
      },
      "name": "netSensibleCoolingCapacity",
      "schema": "double",
      "writable": true
    },
    {
      "@type": "Property",
      "displayName": {
        "en": "Humidification method"
      },
      "name": "humidificationMethod",
      "schema": {
        "@type": "Enum",
        "enumValues": [
          {
            "enumValue": "Ultrasonic",
            "name": "Ultrasonic",
            "displayName": {
              "en": "Ultrasonic"
            }
          },
          {
            "enumValue": "Steam",
            "name": "Steam",
            "displayName": {
              "en": "Steam"
            }
          },
          {
            "enumValue": "None",
            "name": "None",
            "displayName": {
              "en": "None"
            }
          },
          {
            "enumValue": "Adiabatic",
            "name": "Adiabatic",
            "displayName": {
              "en": "Adiabatic"
            }
          }
        ],
        "valueSchema": "string"
      },
      "writable": true
    },
    {
      "@type": "Property",
      "displayName": {
        "en": "Filter type"
      },
      "name": "filterType",
      "schema": "string",
      "writable": true
    },
    {
      "@type": "Property",
      "displayName": {
        "en": "Discharge ductwork configuration"
      },
      "name": "dischargeDuctworkConfiguration",
      "schema": {
        "@type": "Enum",
        "enumValues": [
          {
            "enumValue": "TripleDuct",
            "name": "TripleDuct",
            "displayName": {
              "en": "Triple-duct"
            }
          },
          {
            "enumValue": "SingleDuct",
            "name": "SingleDuct",
            "displayName": {
              "en": "Single-duct"
            }
          },
          {
            "enumValue": "DualDuct",
            "name": "DualDuct",
            "displayName": {
              "en": "Dual-duct"
            }
          }
        ],
        "valueSchema": "string"
      },
      "writable": true
    },
    {
      "@type": "Property",
      "displayName": {
        "en": "Dehumidification method"
      },
      "name": "dehumidificationMethod",
      "schema": {
        "@type": "Enum",
        "enumValues": [
          {
            "enumValue": "WrapAroundCoil",
            "name": "WrapAroundCoil",
            "displayName": {
              "en": "Wrap-around coil"
            }
          },
          {
            "enumValue": "TieredCooling",
            "name": "TieredCooling",
            "displayName": {
              "en": "Tiered cooling"
            }
          },
          {
            "enumValue": "None",
            "name": "None",
            "displayName": {
              "en": "None"
            }
          },
          {
            "enumValue": "DualWheel",
            "name": "DualWheel",
            "displayName": {
              "en": "Dual-wheel"
            }
          },
          {
            "enumValue": "Desiccant",
            "name": "Desiccant",
            "displayName": {
              "en": "Desiccant"
            }
          },
          {
            "enumValue": "CoolReheat",
            "name": "CoolReheat",
            "displayName": {
              "en": "Cool reheat"
            }
          }
        ],
        "valueSchema": "string"
      },
      "writable": true
    },
    {
      "@type": "Property",
      "displayName": {
        "en": "Airflow modulation"
      },
      "name": "airflowModulation",
      "schema": {
        "@type": "Enum",
        "enumValues": [
          {
            "enumValue": "VariableVolume",
            "name": "VariableVolume",
            "displayName": {
              "en": "Variable volume"
            }
          },
          {
            "enumValue": "ConstantVolume",
            "name": "ConstantVolume",
            "displayName": {
              "en": "Constant volume"
            }
          }
        ],
        "valueSchema": "string"
      },
      "writable": true
    },
    {
      "@type": "Component",
      "displayName": {
        "en": "Supply fan"
      },
      "name": "supplyFan",
      "schema": "dtmi:no:energymanager:asset:Fan;1"
    },
    {
      "@type": "Component",
      "displayName": {
        "en": "Secondary cooling method"
      },
      "name": "secondaryCoolingMethod",
      "schema": "dtmi:no:energymanager:asset:HVACCoolingMethod;1"
    },
    {
      "@type": "Component",
      "displayName": {
        "en": "Return fan"
      },
      "name": "returnFan",
      "schema": "dtmi:no:energymanager:asset:Fan;1"
    },
    {
      "@type": "Component",
      "displayName": {
        "en": "Re-heating method"
      },
      "name": "reHeatingMethod",
      "schema": "dtmi:no:energymanager:asset:HVACHeatingMethod;1"
    },
    {
      "@type": "Component",
      "displayName": {
        "en": "Primary cooling method"
      },
      "name": "primaryCoolingMethod",
      "schema": "dtmi:no:energymanager:asset:HVACCoolingMethod;1"
    },
    {
      "@type": "Component",
      "displayName": {
        "en": "Pre-heating method"
      },
      "name": "preHeatingMethod",
      "schema": "dtmi:no:energymanager:asset:HVACHeatingMethod;1"
    },
    {
      "@type": "Component",
      "displayName": {
        "en": "Mixing box"
      },
      "name": "mixingBox",
      "schema": "dtmi:no:energymanager:asset:HVACMixingBox;1"
    },
    {
      "@type": "Component",
      "displayName": {
        "en": "Exhaust fan"
      },
      "name": "exhaustFan",
      "schema": "dtmi:no:energymanager:asset:Fan;1"
    }
  ],
  "displayName": {
    "en": "Air handling unit"
  },
  "extends": "dtmi:no:energymanager:asset:HVACEquipment;1",
  "@context": "dtmi:dtdl:context;2"
}