{
  "@id": "dtmi:no:energymanager:asset:DuctConnection;1",
  "@type": "Interface",
  "contents": [
    {
      "@type": "Property",
      "displayName": {
        "en": "Size"
      },
      "name": "size",
      "schema": "double",
      "writable": true
    },
    {
      "@type": "Property",
      "displayName": {
        "en": "Shape"
      },
      "name": "shape",
      "schema": {
        "@type": "Enum",
        "enumValues": [
          {
            "enumValue": "Round",
            "name": "Round",
            "displayName": {
              "en": "Round"
            }
          },
          {
            "enumValue": "Rectangle",
            "name": "Rectangle",
            "displayName": {
              "en": "Rectangle"
            }
          },
          {
            "enumValue": "Oval",
            "name": "Oval",
            "displayName": {
              "en": "Oval"
            }
          }
        ],
        "valueSchema": "string"
      },
      "writable": true
    },
    {
      "@type": "Property",
      "displayName": {
        "en": "Configuration"
      },
      "name": "configuration",
      "schema": {
        "@type": "Enum",
        "enumValues": [
          {
            "enumValue": "Single",
            "name": "Single",
            "displayName": {
              "en": "Single"
            }
          },
          {
            "enumValue": "Dual",
            "name": "Dual",
            "displayName": {
              "en": "Dual"
            }
          }
        ],
        "valueSchema": "string"
      },
      "writable": true
    }
  ],
  "displayName": {
    "en": "Duct connection"
  },
  "extends": "dtmi:no:energymanager:asset:Component;1",
  "@context": "dtmi:dtdl:context;2"
}